{
  "schema_version": "mgt-uncoarsened-boundary-pdelta-probe.v1",
  "generated_at": "2026-06-03T06:53:26.361347+00:00",
  "status": "partial",
  "uncoarsened_boundary_pdelta_ready": false,
  "full_load_nonlinear_newton_ready": false,
  "roundtrip_policy": {
    "resolve_rigid_links": false,
    "drop_unreferenced_nodes": false,
    "parser_report_contract_pass": true,
    "parser_coarsening": {
      "applied": false,
      "elastic_link_count": 1692,
      "rigid_like_link_count": 0,
      "merge_pair_count": 0,
      "merged_node_count": 0,
      "dummy_node_removed_count": 0,
      "dropped_degenerate_elements": 0,
      "support_node_count": 2133,
      "support_node_count_mapped": 2133,
      "node_count_pre": 13047,
      "node_count_post": 13047,
      "element_count_pre": 12728,
      "element_count_post": 12728
    },
    "parser_run": {
      "command": [
        "/usr/bin/python3",
        "/home/betelgeuze/\uac74\ucd95\uad6c\uc870\ubd84\uc11d/implementation/phase1/parse_midas_mgt_to_json_npz.py",
        "--mgt",
        "/home/betelgeuze/\uac74\ucd95\uad6c\uc870\ubd84\uc11d/implementation/phase1/open_data/midas/midas_generator_33.optimized.mgt",
        "--json-out",
        "/tmp/mgt-uncoarsened-boundary-pdelta-162u3npp/mgt_uncoarsened.roundtrip.json",
        "--npz-out",
        "/tmp/mgt-uncoarsened-boundary-pdelta-162u3npp/mgt_uncoarsened.roundtrip.npz",
        "--report-out",
        "/tmp/mgt-uncoarsened-boundary-pdelta-162u3npp/mgt_uncoarsened.report.json",
        "--no-resolve-rigid-links",
        "--no-drop-unreferenced-nodes",
        "--no-strict-unknown-sections",
        "--max-element-skip-ratio",
        "0.20",
        "--max-element-skip-count",
        "10000"
      ],
      "return_code": 0,
      "stdout_excerpt": "Wrote MIDAS MGT conversion report: /tmp/mgt-uncoarsened-boundary-pdelta-162u3npp/mgt_uncoarsened.report.json\n",
      "stderr_excerpt": "{\"contract_pass\": true, \"event\": \"mgt_parser.completed\", \"reason_code\": \"PASS\"}\n"
    }
  },
  "source": {
    "mgt_path": "/home/betelgeuze/\uac74\ucd95\uad6c\uc870\ubd84\uc11d/implementation/phase1/open_data/midas/midas_generator_33.optimized.mgt",
    "source_family": "midas_mgt",
    "provenance": "repo_benchmark_bridge",
    "blocks": [
      "*CONSTRAINT",
      "*ELASTICLINK",
      "*ELEMENT",
      "*THICKNESS"
    ]
  },
  "solve_scope": "uncoarsened_frame_shell_boundary_tangent_deformed_state_pdelta_probe",
  "unit_policy": {
    "mgt_force_unit": "kN",
    "mgt_length_unit": "m",
    "elastic_link_stiffness_scale_to_si": 1000.0,
    "base_frame_gravity_load_scale": 0.01,
    "load_scale_multiplies_frame_gravity_and_shell_surface_probe_load": true
  },
  "load_steps_requested": [
    0.5405,
    0.5406,
    0.5407,
    0.5408,
    0.5409,
    0.541
  ],
  "max_converged_load_scale": 0.5406,
  "first_failed_load_scale": 0.5407,
  "step_results": [
    {
      "load_scale": 0.5406,
      "ready": true,
      "converged": true,
      "iteration_count": 2,
      "max_iterations": 16,
      "relaxation_factor": 0.5,
      "residual_tolerance_n": 0.0005,
      "relative_increment_tolerance": 0.0001,
      "best_residual_inf_n": 4.47679634785203e-05,
      "best_relative_residual_inf": 6.261359364233225e-09,
      "best_fixed_point_relative_increment": 8.989245171339526e-05,
      "final_residual_inf_n": 4.47679634785203e-05,
      "final_fixed_point_relative_increment": 8.989245171339526e-05,
      "final_max_translation_m": 0.7667092555554126,
      "rows": [
        {
          "iteration": 1,
          "load_scale": 0.5406,
          "residual_inf_n": 5.5699742858905665e-05,
          "relative_residual_inf": 7.790305375453642e-09,
          "rhs_inf_n": 7149.879263322482,
          "regularization": 382.23368967199343,
          "active_dof_count": 61446,
          "free_dof_count": 58998,
          "fixed_point_increment_m": 0.00020231661703107306,
          "fixed_point_relative_increment": 0.0002638679632173259,
          "relaxed_increment_m": 0.00010115830851553653,
          "relaxed_relative_increment": 0.00013195139048098787,
          "max_abs_displacement_m": 0.7666331377547086,
          "max_translation_m": 0.7666846816294863,
          "max_drift_ratio_pct": 0.18779397027276223,
          "displacement_cap_m": 5.0,
          "displacement_cap_exceeded": false,
          "frame_stiffness_nnz": 291132,
          "shell_stiffness_nnz": 1901664,
          "spring_stiffness_nnz": 40608,
          "coupled_stiffness_nnz": 2000590,
          "frame_total_gravity_n": 129592198.79379755,
          "surface_total_area_m2": 11403.932279105049,
          "seconds": 11.020014226000058,
          "residual_gate_passed": true,
          "relative_increment_gate_passed": false,
          "ready": false
        },
        {
          "iteration": 2,
          "load_scale": 0.5406,
          "residual_inf_n": 4.47679634785203e-05,
          "relative_residual_inf": 6.261359364233225e-09,
          "rhs_inf_n": 7149.879263319148,
          "regularization": 382.23369242976577,
          "active_dof_count": 61446,
          "free_dof_count": 58998,
          "fixed_point_increment_m": 6.891896094979929e-05,
          "fixed_point_relative_increment": 8.989245171339526e-05,
          "relaxed_increment_m": 3.445948047489964e-05,
          "relaxed_relative_increment": 4.494766999268133e-05,
          "max_abs_displacement_m": 0.7666577707033658,
          "max_translation_m": 0.7667092555554126,
          "max_drift_ratio_pct": 0.18782861609599663,
          "displacement_cap_m": 5.0,
          "displacement_cap_exceeded": false,
          "frame_stiffness_nnz": 291132,
          "shell_stiffness_nnz": 1901664,
          "spring_stiffness_nnz": 40608,
          "coupled_stiffness_nnz": 2000566,
          "frame_total_gravity_n": 129592198.79379755,
          "surface_total_area_m2": 11403.932245448508,
          "seconds": 10.949999475997174,
          "residual_gate_passed": true,
          "relative_increment_gate_passed": true,
          "ready": true
        }
      ],
      "seconds": 21.99304468599439,
      "blockers": []
    },
    {
      "load_scale": 0.5407,
      "ready": false,
      "converged": false,
      "iteration_count": 16,
      "max_iterations": 16,
      "relaxation_factor": 0.5,
      "residual_tolerance_n": 0.0005,
      "relative_increment_tolerance": 0.0001,
      "best_residual_inf_n": 2.797701422885268e-05,
      "best_relative_residual_inf": 3.9122115181949064e-09,
      "best_fixed_point_relative_increment": 0.00016763201391602618,
      "final_residual_inf_n": 2.912080658923344e-05,
      "final_fixed_point_relative_increment": 0.018523320105347383,
      "final_max_translation_m": 0.7616681568541821,
      "rows": [
        {
          "iteration": 1,
          "load_scale": 0.5407,
          "residual_inf_n": 4.791018107574985e-05,
          "relative_residual_inf": 6.699598488598461e-09,
          "rhs_inf_n": 7151.201845496346,
          "regularization": 382.23369330691554,
          "active_dof_count": 61446,
          "free_dof_count": 58998,
          "fixed_point_increment_m": 0.00022704748231694438,
          "fixed_point_relative_increment": 0.0002960646461278234,
          "relaxed_increment_m": 0.00011352374115847219,
          "relaxed_relative_increment": 0.00014805423987698018,
          "max_abs_displacement_m": 0.7667712944445243,
          "max_translation_m": 0.7668228717056346,
          "max_drift_ratio_pct": 0.18786884456558603,
          "displacement_cap_m": 5.0,
          "displacement_cap_exceeded": false,
          "frame_stiffness_nnz": 291132,
          "shell_stiffness_nnz": 1901664,
          "spring_stiffness_nnz": 40608,
          "coupled_stiffness_nnz": 2000588,
          "frame_total_gravity_n": 129592198.79379755,
          "surface_total_area_m2": 11403.932225632334,
          "seconds": 10.976278734000516,
          "residual_gate_passed": true,
          "relative_increment_gate_passed": false,
          "ready": false
        },
        {
          "iteration": 2,
          "load_scale": 0.5407,
          "residual_inf_n": 4.155812163197936e-05,
          "relative_residual_inf": 5.811347872689162e-09,
          "rhs_inf_n": 7151.201845493482,
          "regularization": 382.23369630526514,
          "active_dof_count": 61446,
          "free_dof_count": 58998,
          "fixed_point_increment_m": 0.0001285389490733907,
          "fixed_point_relative_increment": 0.00016763201391602618,
          "relaxed_increment_m": 6.426947453669536e-05,
          "relaxed_relative_increment": 8.381715877607614e-05,
          "max_abs_displacement_m": 0.7667818317296594,
          "max_translation_m": 0.766833295347623,
          "max_drift_ratio_pct": 0.18790035290678775,
          "displacement_cap_m": 5.0,
          "displacement_cap_exceeded": false,
          "frame_stiffness_nnz": 291132,
          "shell_stiffness_nnz": 1901664,
          "spring_stiffness_nnz": 40608,
          "coupled_stiffness_nnz": 2000628,
          "frame_total_gravity_n": 129592198.79379755,
          "surface_total_area_m2": 11403.93219369343,
          "seconds": 10.943559315986931,
          "residual_gate_passed": true,
          "relative_increment_gate_passed": false,
          "ready": false
        },
        {
          "iteration": 3,
          "load_scale": 0.5407,
          "residual_inf_n": 5.963144765175343e-05,
          "relative_residual_inf": 8.338660960793676e-09,
          "rhs_inf_n": 7151.201845491233,
          "regularization": 382.2336969095328,
          "active_dof_count": 61446,
          "free_dof_count": 58998,
          "fixed_point_increment_m": 0.0001631659329135487,
          "fixed_point_relative_increment": 0.00021275863336615416,
          "relaxed_increment_m": 8.158296645677438e-05,
          "relaxed_relative_increment": 0.0001063879489155622,
          "max_abs_displacement_m": 0.7668440578878442,
          "max_translation_m": 0.7668956811991319,
          "max_drift_ratio_pct": 0.1879216816713163,
          "displacement_cap_m": 5.0,
          "displacement_cap_exceeded": false,
          "frame_stiffness_nnz": 291132,
          "shell_stiffness_nnz": 1901664,
          "spring_stiffness_nnz": 40608,
          "coupled_stiffness_nnz": 2000609,
          "frame_total_gravity_n": 129592198.79379755,
          "surface_total_area_m2": 11403.932173049947,
          "seconds": 10.971898162009893,
          "residual_gate_passed": true,
          "relative_increment_gate_passed": false,
          "ready": false
        },
        {
          "iteration": 4,
          "load_scale": 0.5407,
          "residual_inf_n": 3.352593935801451e-05,
          "relative_residual_inf": 4.6881545343541715e-09,
          "rhs_inf_n": 7151.201845489712,
          "regularization": 382.2336983009076,
          "active_dof_count": 61446,
          "free_dof_count": 58998,
          "fixed_point_increment_m": 0.0002435139755973992,
          "fixed_point_relative_increment": 0.00031759606137738415,
          "relaxed_increment_m": 0.0001217569877986996,
          "relaxed_relative_increment": 0.00015878737693504253,
          "max_abs_displacement_m": 0.7667926138014642,
          "max_translation_m": 0.7668440118909354,
          "max_drift_ratio_pct": 0.18793514724876867,
          "displacement_cap_m": 5.0,
          "displacement_cap_exceeded": false,
          "frame_stiffness_nnz": 291132,
          "shell_stiffness_nnz": 1901664,
          "spring_stiffness_nnz": 40608,
          "coupled_stiffness_nnz": 2000588,
          "frame_total_gravity_n": 129592198.79379755,
          "surface_total_area_m2": 11403.932166993856,
          "seconds": 11.04377099100384,
          "residual_gate_passed": true,
          "relative_increment_gate_passed": false,
          "ready": false
        },
        {
          "iteration": 5,
          "load_scale": 0.5407,
          "residual_inf_n": 6.325050907918239e-05,
          "relative_residual_inf": 8.844738331513224e-09,
          "rhs_inf_n": 7151.201845488743,
          "regularization": 382.23369738811493,
          "active_dof_count": 61446,
          "free_dof_count": 58998,
          "fixed_point_increment_m": 0.00029445405665216666,
          "fixed_point_relative_increment": 0.0003839264010000142,
          "relaxed_increment_m": 0.00014722702832608333,
          "relaxed_relative_increment": 0.00019198345420545098,
          "max_abs_displacement_m": 0.7668735253014481,
          "max_translation_m": 0.7669252074313173,
          "max_drift_ratio_pct": 0.18794317702027638,
          "displacement_cap_m": 5.0,
          "displacement_cap_exceeded": false,
          "frame_stiffness_nnz": 291132,
          "shell_stiffness_nnz": 1901664,
          "spring_stiffness_nnz": 40608,
          "coupled_stiffness_nnz": 2000629,
          "frame_total_gravity_n": 129592198.79379755,
          "surface_total_area_m2": 11403.932156074077,
          "seconds": 11.012052916004905,
          "residual_gate_passed": true,
          "relative_increment_gate_passed": false,
          "ready": false
        },
        {
          "iteration": 6,
          "load_scale": 0.5407,
          "residual_inf_n": 4.52041368017575e-05,
          "relative_residual_inf": 6.321194364032339e-09,
          "rhs_inf_n": 7151.201845488173,
          "regularization": 382.2336989575261,
          "active_dof_count": 61446,
          "free_dof_count": 58998,
          "fixed_point_increment_m": 0.00047071374142092833,
          "fixed_point_relative_increment": 0.0006139922821313531,
          "relaxed_increment_m": 0.00023535687071046417,
          "relaxed_relative_increment": 0.0003069502712120549,
          "max_abs_displacement_m": 0.7667589599484966,
          "max_translation_m": 0.7668102080012705,
          "max_drift_ratio_pct": 0.18794793491262393,
          "displacement_cap_m": 5.0,
          "displacement_cap_exceeded": false,
          "frame_stiffness_nnz": 291132,
          "shell_stiffness_nnz": 1901664,
          "spring_stiffness_nnz": 40608,
          "coupled_stiffness_nnz": 2000567,
          "frame_total_gravity_n": 129592198.79379755,
          "surface_total_area_m2": 11403.932158981052,
          "seconds": 11.008582294991356,
          "residual_gate_passed": true,
          "relative_increment_gate_passed": false,
          "ready": false
        },
        {
          "iteration": 7,
          "load_scale": 0.5407,
          "residual_inf_n": 7.71675159487728e-05,
          "relative_residual_inf": 1.0790845736994964e-08,
          "rhs_inf_n": 7151.201845487823,
          "regularization": 382.23369669664925,
          "active_dof_count": 61446,
          "free_dof_count": 58998,
          "fixed_point_increment_m": 0.0005139175214652378,
          "fixed_point_relative_increment": 0.0006700070888769104,
          "relaxed_increment_m": 0.0002569587607326189,
          "relaxed_relative_increment": 0.0003350633905092671,
          "max_abs_displacement_m": 0.7668959606182699,
          "max_translation_m": 0.7669477123809729,
          "max_drift_ratio_pct": 0.18795053087941901,
          "displacement_cap_m": 5.0,
          "displacement_cap_exceeded": false,
          "frame_stiffness_nnz": 291132,
          "shell_stiffness_nnz": 1901664,
          "spring_stiffness_nnz": 40608,
          "coupled_stiffness_nnz": 2000626,
          "frame_total_gravity_n": 129592198.79379755,
          "surface_total_area_m2": 11403.932145573874,
          "seconds": 10.97465791698778,
          "residual_gate_passed": true,
          "relative_increment_gate_passed": false,
          "ready": false
        },
        {
          "iteration": 8,
          "load_scale": 0.5407,
          "residual_inf_n": 4.038283405272125e-05,
          "relative_residual_inf": 5.6469996128276695e-09,
          "rhs_inf_n": 7151.201845487646,
          "regularization": 382.2336992016998,
          "active_dof_count": 61446,
          "free_dof_count": 58998,
          "fixed_point_increment_m": 0.0009368368801124294,
          "fixed_point_relative_increment": 0.0012223212035349373,
          "relaxed_increment_m": 0.0004684184400562146,
          "relaxed_relative_increment": 0.0006109791956147946,
          "max_abs_displacement_m": 0.7666683962698124,
          "max_translation_m": 0.7667192997723928,
          "max_drift_ratio_pct": 0.18795213399613772,
          "displacement_cap_m": 5.0,
          "displacement_cap_exceeded": false,
          "frame_stiffness_nnz": 291132,
          "shell_stiffness_nnz": 1901664,
          "spring_stiffness_nnz": 40608,
          "coupled_stiffness_nnz": 2000588,
          "frame_total_gravity_n": 129592198.79379755,
          "surface_total_area_m2": 11403.93215341993,
          "seconds": 10.861822553997627,
          "residual_gate_passed": true,
          "relative_increment_gate_passed": false,
          "ready": false
        },
        {
          "iteration": 9,
          "load_scale": 0.5407,
          "residual_inf_n": 3.685634283812078e-05,
          "relative_residual_inf": 5.153866949144712e-09,
          "rhs_inf_n": 7151.201845487517,
          "regularization": 382.2336945584194,
          "active_dof_count": 61446,
          "free_dof_count": 58998,
          "fixed_point_increment_m": 0.0008375359552674396,
          "fixed_point_relative_increment": 0.001091776102373597,
          "relaxed_increment_m": 0.0004187679776337198,
          "relaxed_relative_increment": 0.0005460529102864464,
          "max_abs_displacement_m": 0.7669000013461041,
          "max_translation_m": 0.7669517582263085,
          "max_drift_ratio_pct": 0.1879528130682605,
          "displacement_cap_m": 5.0,
          "displacement_cap_exceeded": false,
          "frame_stiffness_nnz": 291132,
          "shell_stiffness_nnz": 1901664,
          "spring_stiffness_nnz": 40608,
          "coupled_stiffness_nnz": 2000570,
          "frame_total_gravity_n": 129592198.79379755,
          "surface_total_area_m2": 11403.932127276563,
          "seconds": 10.982979264997994,
          "residual_gate_passed": true,
          "relative_increment_gate_passed": false,
          "ready": false
        },
        {
          "iteration": 10,
          "load_scale": 0.5407,
          "residual_inf_n": 3.7007119585652504e-05,
          "relative_residual_inf": 5.174951062107768e-09,
          "rhs_inf_n": 7151.201845487488,
          "regularization": 382.23369850435824,
          "active_dof_count": 61446,
          "free_dof_count": 58998,
          "fixed_point_increment_m": 0.001941508609426031,
          "fixed_point_relative_increment": 0.002534668896154825,
          "relaxed_increment_m": 0.0009707543047130156,
          "relaxed_relative_increment": 0.0012665747771672096,
          "max_abs_displacement_m": 0.7664405783322017,
          "max_translation_m": 0.7664906295534336,
          "max_drift_ratio_pct": 0.18795346098838772,
          "displacement_cap_m": 5.0,
          "displacement_cap_exceeded": false,
          "frame_stiffness_nnz": 291132,
          "shell_stiffness_nnz": 1901664,
          "spring_stiffness_nnz": 40608,
          "coupled_stiffness_nnz": 2000627,
          "frame_total_gravity_n": 129592198.79379755,
          "surface_total_area_m2": 11403.932136620238,
          "seconds": 10.952933284002938,
          "residual_gate_passed": true,
          "relative_increment_gate_passed": false,
          "ready": false
        },
        {
          "iteration": 11,
          "load_scale": 0.5407,
          "residual_inf_n": 7.986987459851491e-05,
          "relative_residual_inf": 1.1168734476277547e-08,
          "rhs_inf_n": 7151.201845487415,
          "regularization": 382.23368880014834,
          "active_dof_count": 61446,
          "free_dof_count": 58998,
          "fixed_point_increment_m": 0.0011618584450585432,
          "fixed_point_relative_increment": 0.0015145034837744573,
          "relaxed_increment_m": 0.0005809292225292716,
          "relaxed_relative_increment": 0.0007576043509142733,
          "max_abs_displacement_m": 0.7667976323369963,
          "max_translation_m": 0.7668489820099795,
          "max_drift_ratio_pct": 0.18795343662114092,
          "displacement_cap_m": 5.0,
          "displacement_cap_exceeded": false,
          "frame_stiffness_nnz": 291132,
          "shell_stiffness_nnz": 1901664,
          "spring_stiffness_nnz": 40608,
          "coupled_stiffness_nnz": 2000588,
          "frame_total_gravity_n": 129592198.79379755,
          "surface_total_area_m2": 11403.932076469604,
          "seconds": 10.944255955997505,
          "residual_gate_passed": true,
          "relative_increment_gate_passed": false,
          "ready": false
        },
        {
          "iteration": 12,
          "load_scale": 0.5407,
          "residual_inf_n": 2.797701422885268e-05,
          "relative_residual_inf": 3.9122115181949064e-09,
          "rhs_inf_n": 7151.201845487452,
          "regularization": 382.2336939103331,
          "active_dof_count": 61446,
          "free_dof_count": 58998,
          "fixed_point_increment_m": 0.004176709626786054,
          "fixed_point_relative_increment": 0.005460535110110876,
          "relaxed_increment_m": 0.002088354813393027,
          "relaxed_relative_increment": 0.0027268674604256932,
          "max_abs_displacement_m": 0.7658439009965716,
          "max_translation_m": 0.7658917407373542,
          "max_drift_ratio_pct": 0.18795392426754712,
          "displacement_cap_m": 5.0,
          "displacement_cap_exceeded": false,
          "frame_stiffness_nnz": 291132,
          "shell_stiffness_nnz": 1901664,
          "spring_stiffness_nnz": 40608,
          "coupled_stiffness_nnz": 2000609,
          "frame_total_gravity_n": 129592198.79379755,
          "surface_total_area_m2": 11403.932072537391,
          "seconds": 10.894870599993737,
          "residual_gate_passed": true,
          "relative_increment_gate_passed": false,
          "ready": false
        },
        {
          "iteration": 13,
          "load_scale": 0.5407,
          "residual_inf_n": 4.702786596588737e-05,
          "relative_residual_inf": 6.5762185129151975e-09,
          "rhs_inf_n": 7151.2018454873705,
          "regularization": 382.2336731099705,
          "active_dof_count": 61446,
          "free_dof_count": 58998,
          "fixed_point_increment_m": 0.0016649412518813045,
          "fixed_point_relative_increment": 0.0021714835270002972,
          "relaxed_increment_m": 0.0008324706259406523,
          "relaxed_relative_increment": 0.0010863694124484838,
          "max_abs_displacement_m": 0.7662868784794035,
          "max_translation_m": 0.7663362432143062,
          "max_drift_ratio_pct": 0.18795352086027603,
          "displacement_cap_m": 5.0,
          "displacement_cap_exceeded": false,
          "frame_stiffness_nnz": 291132,
          "shell_stiffness_nnz": 1901664,
          "spring_stiffness_nnz": 40608,
          "coupled_stiffness_nnz": 2000647,
          "frame_total_gravity_n": 129592198.79379755,
          "surface_total_area_m2": 11403.93192208545,
          "seconds": 10.859706524992362,
          "residual_gate_passed": true,
          "relative_increment_gate_passed": false,
          "ready": false
        },
        {
          "iteration": 14,
          "load_scale": 0.5407,
          "residual_inf_n": 7.3201344518381e-05,
          "relative_residual_inf": 1.023622967160022e-08,
          "rhs_inf_n": 7151.201845487462,
          "regularization": 382.23367626236484,
          "active_dof_count": 61446,
          "free_dof_count": 58998,
          "fixed_point_increment_m": 0.008703146471152882,
          "fixed_point_relative_increment": 0.011414979931943153,
          "relaxed_increment_m": 0.004351573235576441,
          "relaxed_relative_increment": 0.005693097892915997,
          "max_abs_displacement_m": 0.7643594607763844,
          "max_translation_m": 0.7644019178931266,
          "max_drift_ratio_pct": 0.18795416213947377,
          "displacement_cap_m": 5.0,
          "displacement_cap_exceeded": false,
          "frame_stiffness_nnz": 291132,
          "shell_stiffness_nnz": 1901664,
          "spring_stiffness_nnz": 40608,
          "coupled_stiffness_nnz": 2000569,
          "frame_total_gravity_n": 129592198.79379755,
          "surface_total_area_m2": 11403.931852401445,
          "seconds": 10.897366940989741,
          "residual_gate_passed": true,
          "relative_increment_gate_passed": false,
          "ready": false
        },
        {
          "iteration": 15,
          "load_scale": 0.5407,
          "residual_inf_n": 3.299735088724276e-05,
          "relative_residual_inf": 4.614238501471644e-09,
          "rhs_inf_n": 7151.20184548734,
          "regularization": 382.233634511335,
          "active_dof_count": 61446,
          "free_dof_count": 58998,
          "fixed_point_increment_m": 0.002063832087409548,
          "fixed_point_relative_increment": 0.002697333973531181,
          "relaxed_increment_m": 0.001031916043704774,
          "relaxed_relative_increment": 0.001349353273027617,
          "max_abs_displacement_m": 0.7647486127850034,
          "max_translation_m": 0.7647920803812371,
          "max_drift_ratio_pct": 0.18795342900916764,
          "displacement_cap_m": 5.0,
          "displacement_cap_exceeded": false,
          "frame_stiffness_nnz": 291132,
          "shell_stiffness_nnz": 1901664,
          "spring_stiffness_nnz": 40608,
          "coupled_stiffness_nnz": 2000570,
          "frame_total_gravity_n": 129592198.79379755,
          "surface_total_area_m2": 11403.931477846276,
          "seconds": 11.023438579999493,
          "residual_gate_passed": true,
          "relative_increment_gate_passed": false,
          "ready": false
        },
        {
          "iteration": 16,
          "load_scale": 0.5407,
          "residual_inf_n": 2.912080658923344e-05,
          "relative_residual_inf": 4.072155592644764e-09,
          "rhs_inf_n": 7151.201845487491,
          "regularization": 382.2336302214693,
          "active_dof_count": 61446,
          "free_dof_count": 58998,
          "fixed_point_increment_m": 0.014050342599213048,
          "fixed_point_relative_increment": 0.018523320105347383,
          "relaxed_increment_m": 0.007025171299606523,
          "relaxed_relative_increment": 0.00922380047352443,
          "max_abs_displacement_m": 0.7616352196441423,
          "max_translation_m": 0.7616681568541821,
          "max_drift_ratio_pct": 0.1879543127814176,
          "displacement_cap_m": 5.0,
          "displacement_cap_exceeded": false,
          "frame_stiffness_nnz": 291132,
          "shell_stiffness_nnz": 1901664,
          "spring_stiffness_nnz": 40608,
          "coupled_stiffness_nnz": 2000627,
          "frame_total_gravity_n": 129592198.79379755,
          "surface_total_area_m2": 11403.931240127002,
          "seconds": 10.981164686992997,
          "residual_gate_passed": true,
          "relative_increment_gate_passed": false,
          "ready": false
        }
      ],
      "seconds": 175.50374969901168,
      "blockers": [
        "uncoarsened_boundary_pdelta_step_not_converged"
      ]
    }
  ],
  "checkpoint_resume": {
    "supported": true,
    "checkpoint_schema_version": "mgt-uncoarsened-boundary-pdelta-checkpoint.v1",
    "checkpoint_dir": "/tmp/mgt_uncoarsened_boundary_pdelta_frontier_checkpoints_05406_0541_16iter_relax05",
    "resume_checkpoint_npz": "implementation/phase1/release_evidence/productization/mgt_uncoarsened_boundary_pdelta_relaxed_checkpoints/accepted_load_0p5405.npz",
    "resume_from_load_scale": 0.5405,
    "resume_checkpoint": {
      "path": "implementation/phase1/release_evidence/productization/mgt_uncoarsened_boundary_pdelta_relaxed_checkpoints/accepted_load_0p5405.npz",
      "schema_version": "mgt-uncoarsened-boundary-pdelta-checkpoint.v1",
      "load_scale": 0.5405,
      "dof_count": 78282,
      "node_count": 13047,
      "residual_inf_n": 1.7422796821264797e-05,
      "fixed_point_relative_increment": 9.563249032919737e-05,
      "max_translation_m": 0.7665834708732076
    },
    "skipped_load_steps_before_resume": [
      0.5405
    ],
    "attempted_load_steps_after_resume": [
      0.5406,
      0.5407,
      0.5408,
      0.5409,
      0.541
    ],
    "saved_checkpoint_count": 1,
    "saved_checkpoints": [
      {
        "path": "/tmp/mgt_uncoarsened_boundary_pdelta_frontier_checkpoints_05406_0541_16iter_relax05/accepted_load_0p5406.npz",
        "schema_version": "mgt-uncoarsened-boundary-pdelta-checkpoint.v1",
        "load_scale": 0.5406,
        "dof_count": 78282,
        "node_count": 13047,
        "residual_inf_n": 4.47679634785203e-05,
        "fixed_point_relative_increment": 8.989245171339526e-05,
        "max_translation_m": 0.7667092555554126
      }
    ],
    "claim_boundary": "Accepted displacement states can be written and replayed as exact seeds for later frontier probes. This reduces rerun cost for bracket search, but it does not change the nonlinear convergence gate or promote a failed residual/increment state."
  },
  "mesh_fingerprint": {
    "raw_line_element_count": 5576,
    "line_elements_solved": 5564,
    "skipped_short_or_degenerate_line_count": 12,
    "line_node_count": 2491,
    "beam_end_offset_applied_element_count": 708,
    "beam_end_offset_max_abs_m": 0.523,
    "frame_local_axis_angle_array_present": true,
    "frame_local_axis_nonzero_angle_count": 150,
    "frame_local_axis_max_abs_angle_deg": 270.0,
    "node_count": 13047,
    "dof_count": 78282,
    "element_count": 12728,
    "elastic_link_spring_stiffness_nnz": 40608
  },
  "boundary_summary": {
    "support_constraint_row_count": 8,
    "authored_support_node_count": 2133,
    "mapped_support_node_count": 2133,
    "missing_support_node_count": 0,
    "authored_support_restrained_dof_count": 7707,
    "restraint_code_counts": {
      "111000": 1,
      "111111": 7
    },
    "restrained_dof_counts": {
      "Dx": 2133,
      "Dy": 2133,
      "Dz": 2133,
      "Rx": 436,
      "Ry": 436,
      "Rz": 436
    },
    "missing_support_node_ids_head": [],
    "elastic_link_row_count": 1692,
    "elastic_link_rows_skipped": 0,
    "distinct_elastic_link_node_count": 3384,
    "mapped_elastic_link_node_count": 3384,
    "missing_elastic_link_node_count": 0,
    "finite_spring_component_count": 10152,
    "finite_spring_dof_counts": {
      "SDx": 1692,
      "SDy": 1692,
      "SDz": 1692,
      "SRx": 1692,
      "SRy": 1692,
      "SRz": 1692
    },
    "elastic_link_type_counts": {
      "GEN": 1692
    },
    "stiffness_abs_min_nonzero_n_per_m_or_nm_per_rad": 1.0,
    "stiffness_abs_max_n_per_m_or_nm_per_rad": 1000000000.0
  },
  "runtime_metrics": {
    "backend": "scipy_sparse_spsolve_cpu_uncoarsened_boundary_pdelta_probe",
    "total_seconds": 199.65848872700008
  },
  "claim_boundary": "This probe wires the uncoarsened authored support masks and finite elastic-link spring tangent into a deformed-coordinate frame-shell P-Delta fixed-point loop. The frame tangent uses geometric stiffness from frame gravity axial forces and the shell tangent is rebuilt on the deformed nodal coordinates. It is a nonlinear path diagnostic only; it is not a consistent Newton/Jacobian, material nonlinear, or full-load closure.",
  "blockers": [
    "uncoarsened_boundary_pdelta_not_full_load_closed",
    "consistent_newton_jacobian_required",
    "material_nonlinear_newton_required"
  ]
}
