{
  "schema_version": "mgt-hip-frame-force-batch-probe.v1",
  "generated_at": "2026-06-14T01:51:26.996016+00:00",
  "status": "pass",
  "mgt_path": "/home/betelgeuze/건축구조분석/implementation/phase1/open_data/midas/midas_generator_33.optimized.mgt",
  "checkpoint_npz": "implementation/phase1/release_evidence/productization/mgt_direct_residual_attached_policy_shell_normal_fastpath_followup40_final_checkpoint.npz",
  "shell_pressure_load_path_policy": "attached_components_only",
  "batch_size": 64,
  "dof_count": 78282,
  "free_dof_count": 58998,
  "frame_element_count": 5564,
  "reps": 20,
  "perturbation_scale": 1e-06,
  "base_direct_residual_inf_n": 0.03405888348788749,
  "rhs_inf_n": 8676.13911480824,
  "prepack_seconds": 0.6291989609999291,
  "cpu_frame_batch_mean_seconds": 0.06942373890015005,
  "hip_frame_batch_kernel_mean_seconds": 0.000537403345,
  "hip_frame_batch_kernel_speedup_vs_cpu": 129.183674694377,
  "hip_subprocess_seconds": 0.3501776000011887,
  "max_abs_frame_force_difference_n": 1.1620006930002091e-06,
  "relative_frame_force_difference_inf": 7.086246274218062e-12,
  "comparison_tolerances": {
    "absolute_tolerance_n": 2e-06,
    "relative_tolerance_inf": 1e-10,
    "pass_rule": "hip_ok_and_abs_le_tolerance_or_relative_le_tolerance"
  },
  "cpu_frame_force_inf_n": 163979.7218490591,
  "hip_frame_force_inf_n": 163979.7218490591,
  "cpu_meta": {
    "frame_internal_force_model": "corotational_force_based_6dof",
    "real_section_material_element_count": 5485,
    "geometric_element_count": 1946,
    "min_chord_length_m": 0.31923032437409377,
    "max_chord_length_ratio": 1.0,
    "element_count": 5564,
    "frame_force_based_fastpath_available": true,
    "frame_force_based_fastpath": true,
    "frame_force_based_batch_fastpath": true,
    "frame_force_based_batch_size": 64,
    "frame_force_based_prepacked_element_count": 5564
  },
  "build": {
    "attempted": true,
    "ok": true,
    "binary": "/home/betelgeuze/건축구조분석/implementation/phase1/release_evidence/productization/bin/hip_frame_force_batch_replay",
    "source": "/home/betelgeuze/건축구조분석/implementation/phase1/hip_frame_force_batch_replay.cpp",
    "command": [
      "/opt/rocm/bin/hipcc",
      "-O3",
      "-std=c++17",
      "--offload-arch=gfx1030",
      "--rocm-device-lib-path=/home/betelgeuze/건축구조분석/implementation/phase1/third_party/rocm_device_libs/opt/rocm-5.7.1/amdgcn/bitcode",
      "/home/betelgeuze/건축구조분석/implementation/phase1/hip_frame_force_batch_replay.cpp",
      "-o",
      "/home/betelgeuze/건축구조분석/implementation/phase1/release_evidence/productization/bin/hip_frame_force_batch_replay"
    ],
    "returncode": 0,
    "stdout": "",
    "stderr": "",
    "seconds": 1.3638979800016386
  },
  "hip": {
    "ok": true,
    "backend": "native_hip_frame_force_batch",
    "element_count": 5564,
    "n_dof": 78282,
    "batch_size": 64,
    "reps": 20,
    "device_count": 1,
    "device_count_query_ok": true,
    "device_count_query_error": "",
    "set_device_ok": true,
    "set_device_error": "",
    "device_props_ok": true,
    "device_name": "AMD Radeon RX 6900 XT",
    "kernel_elapsed_ms_total": 10.748066902,
    "kernel_elapsed_ms_mean": 0.537403345,
    "output_abs_sum": 562492662.4772847,
    "output_max_abs": 163979.721849059,
    "command": [
      "/home/betelgeuze/건축구조분석/implementation/phase1/release_evidence/productization/bin/hip_frame_force_batch_replay",
      "--dofs",
      "/tmp/mgt_hip_frame_batch_p3o0f2ed/dofs.i64",
      "--stiffness",
      "/tmp/mgt_hip_frame_batch_p3o0f2ed/stiffness.f64",
      "--states",
      "/tmp/mgt_hip_frame_batch_p3o0f2ed/states.f64",
      "--output",
      "/tmp/mgt_hip_frame_batch_p3o0f2ed/hip_frame_force.f64",
      "--element-count",
      "5564",
      "--n-dof",
      "78282",
      "--batch-size",
      "64",
      "--reps",
      "20"
    ],
    "returncode": 0,
    "stdout": "{\"ok\":true,\"backend\":\"native_hip_frame_force_batch\",\"element_count\":5564,\"n_dof\":78282,\"batch_size\":64,\"reps\":20,\"device_count\":1,\"device_count_query_ok\":true,\"device_count_query_error\":\"\",\"set_device_ok\":true,\"set_device_error\":\"\",\"device_props_ok\":true,\"device_name\":\"AMD Radeon RX 6900 XT\",\"kernel_elapsed_ms_total\":10.748066902,\"kernel_elapsed_ms_mean\":0.537403345,\"output_abs_sum\":562492662.477284670,\"output_max_abs\":163979.721849059}\n",
    "stderr": "",
    "subprocess_seconds": 0.3501776000011887
  },
  "runtime_seconds": 27.286624413001846,
  "claim_boundary": "Validates native HIP frame-force batch replay against the G1 prepacked CPU frame path. This covers frame internal-force replay only; shell CSR batch matvec and full residual gate closure remain separate work."
}
