{
  "schema_version": "mgt-rocm-sparse-solver-probe.v1",
  "generated_at": "2026-06-05T15:34:03.683083+00:00",
  "status": "partial",
  "label": "surface_shell_bending_rocm_energy_smoothed_projected_fgmres_focused_probe",
  "roundtrip_json": "/home/betelgeuze/건축구조분석/implementation/phase1/open_data/midas/midas_generator_33.optimized.roundtrip.json",
  "roundtrip_npz": "/home/betelgeuze/건축구조분석/implementation/phase1/open_data/midas/midas_generator_33.optimized.roundtrip.npz",
  "mgt_path": "/home/betelgeuze/건축구조분석/implementation/phase1/open_data/midas/midas_generator_33.optimized.mgt",
  "torch_rocm": {
    "torch_import_ok": true,
    "torch_version": "2.6.0+rocm6.1",
    "torch_version_hip": "6.1.40091-a8dbc0c19",
    "torch_cuda_api_available": true,
    "torch_cuda_device_count": 1,
    "device_name": "AMD Radeon RX 6900 XT"
  },
  "matrix_shape": [
    33932,
    33932
  ],
  "matrix_nnz": 823815,
  "mesh_fingerprint": {
    "surface_element_count": 7152,
    "surface_quad_count": 6968,
    "surface_tri_count": 184,
    "assembled_triangle_count": 14120,
    "skipped_degenerate_triangle_count": 0,
    "surface_node_count": 7894,
    "surface_material_coverage_pct": 96.33668903803132,
    "unique_surface_material_count": 20,
    "unique_surface_section_count": 15,
    "surface_total_area_m2": 11404.192103423085,
    "surface_stiffness_nnz": 1901664,
    "thickness_policy": "source_mgt_thickness_rows_by_plate_section_id",
    "source_plate_thickness_coverage_count": 7152,
    "source_plate_thickness_coverage_pct": 100.0,
    "source_thickness_table_count": 25,
    "thickness_min_m": 0.140625,
    "thickness_max_m": 0.85,
    "combined_component_count": 3,
    "combined_base_node_count": 404,
    "restrained_dof_count": 2424,
    "free_dof_count": 33932
  },
  "cpu_reference": {
    "backend": "scipy_sparse_spsolve_cpu",
    "residual_inf_n": 4.256728516338626e-07,
    "relative_residual_inf": 1.310820378513631e-08,
    "rhs_inf_n": 32.47377433333335,
    "solve_seconds": 0.4242320209996251
  },
  "gate": {
    "tolerance_abs": 0.001,
    "tolerance_rel": 5e-08
  },
  "best_residual_inf_n": 24.324310976328043,
  "best_converged": false,
  "best_row": {
    "backend": "rocm_torch_sparse_multilevel_projected_fgmres",
    "device": "cuda:0",
    "converged": false,
    "aggregate_count": 512,
    "projector_kind": "distributed_structural_node_dof_orthogonal_projection",
    "level_count": 4,
    "levels": [
      {
        "level": 0,
        "size": 33932,
        "nnz": 823815,
        "projector_columns": 2407,
        "projector_nnz": 416272,
        "projector_smoothing_steps_applied": 1
      },
      {
        "level": 1,
        "size": 2407,
        "nnz": 423333,
        "projector_columns": 602,
        "projector_nnz": 157792,
        "projector_smoothing_steps_applied": 1
      },
      {
        "level": 2,
        "size": 602,
        "nnz": 295290,
        "projector_columns": 151,
        "projector_nnz": 73977,
        "projector_smoothing_steps_applied": 1
      },
      {
        "level": 3,
        "size": 151,
        "nnz": 18511,
        "projector_columns": null,
        "projector_nnz": null,
        "projector_smoothing_steps_applied": null
      }
    ],
    "pre_smooth_steps": 1,
    "post_smooth_steps": 1,
    "smoother_weight": 0.05,
    "coarse_regularization_factor": 1e-08,
    "prolongation_smoothing_steps": 1,
    "prolongation_smoothing_weight": 0.02,
    "projector_smoothing_steps_applied": [
      1,
      1,
      1
    ],
    "krylov_method": "fgmres",
    "restart_dimension": 24,
    "restart_cycles": 2,
    "iteration_count": 48,
    "max_iterations": 48,
    "initial_residual_inf_n": 32.47377433333335,
    "residual_inf_n": 24.324310976328043,
    "best_residual_inf_n": 24.324310976328043,
    "relative_residual_inf": 0.7490447746124745,
    "rhs_inf_n": 32.47377433333335,
    "threshold_n": 0.001,
    "residual_history_head": [
      32.47377433333335,
      33.0640402480153,
      30.93406193292241,
      28.72821318090427,
      27.525118805012205,
      27.00336748333812,
      27.711861395037918,
      28.189713423318814
    ],
    "residual_history_tail": [
      26.91338765036194,
      26.871747669562318,
      26.65146492619111,
      26.002504006355714,
      25.330219347378467,
      24.896663688035677,
      24.324310976328043,
      24.33429509720904
    ],
    "solve_seconds": 1.2943172350005625,
    "device_residency_ratio": 1.0,
    "vcycle_count": 48,
    "host_dense_solve_fallback_count": 0,
    "host_copy_bytes": 692971824,
    "hip_kernel_invocation_count": 1344,
    "solver_path_kind": "rocm_sparse_multilevel_projected_fgmres_probe",
    "breakdown": "multilevel_projected_fgmres_residual_gate_not_met",
    "claim_boundary": "Recursive projected V-cycle FGMRES uses distributed structural-node DOF modes as the first-level orthogonal projection basis when authored free_global_dof metadata is available, then algebraic RCM aggregation on coarser levels. Sparse matvecs, restrictions, prolongations, Jacobi smoothing, Arnoldi updates, least-squares solves, and coarse dense solves run on the ROCm torch device; CPU work is hierarchy setup only and cannot promote closure without full assembled CSR residual replay."
  },
  "rows": [
    {
      "backend": "rocm_torch_sparse_multilevel_projected_fgmres",
      "device": "cuda:0",
      "converged": false,
      "aggregate_count": 256,
      "projector_kind": "distributed_structural_node_dof_orthogonal_projection",
      "level_count": 4,
      "levels": [
        {
          "level": 0,
          "size": 33932,
          "nnz": 823815,
          "projector_columns": 1225,
          "projector_nnz": 369392,
          "projector_smoothing_steps_applied": 1
        },
        {
          "level": 1,
          "size": 1225,
          "nnz": 212837,
          "projector_columns": 307,
          "projector_nnz": 74548,
          "projector_smoothing_steps_applied": 1
        },
        {
          "level": 2,
          "size": 307,
          "nnz": 77853,
          "projector_columns": 77,
          "projector_nnz": 19555,
          "projector_smoothing_steps_applied": 1
        },
        {
          "level": 3,
          "size": 77,
          "nnz": 4907,
          "projector_columns": null,
          "projector_nnz": null,
          "projector_smoothing_steps_applied": null
        }
      ],
      "pre_smooth_steps": 1,
      "post_smooth_steps": 1,
      "smoother_weight": 0.05,
      "coarse_regularization_factor": 1e-08,
      "prolongation_smoothing_steps": 1,
      "prolongation_smoothing_weight": 0.02,
      "projector_smoothing_steps_applied": [
        1,
        1,
        1
      ],
      "krylov_method": "fgmres",
      "restart_dimension": 24,
      "restart_cycles": 2,
      "iteration_count": 48,
      "max_iterations": 48,
      "initial_residual_inf_n": 32.47377433333335,
      "residual_inf_n": 24.75141369333487,
      "best_residual_inf_n": 24.75141369333487,
      "relative_residual_inf": 0.7621970097860873,
      "rhs_inf_n": 32.47377433333335,
      "threshold_n": 0.001,
      "residual_history_head": [
        32.47377433333335,
        32.41303245265984,
        31.950377950590255,
        29.915741408206955,
        28.602850813616776,
        28.099375652911036,
        28.737211344583393,
        27.908289414097524
      ],
      "residual_history_tail": [
        27.601329601351864,
        27.359224690154804,
        26.36975640650538,
        26.052413081854514,
        26.02861687435058,
        25.45962554973413,
        25.11459359537182,
        24.75141369333487
      ],
      "solve_seconds": 1.1844759650011838,
      "device_residency_ratio": 1.0,
      "vcycle_count": 48,
      "host_dense_solve_fallback_count": 0,
      "host_copy_bytes": 355329132,
      "hip_kernel_invocation_count": 1344,
      "solver_path_kind": "rocm_sparse_multilevel_projected_fgmres_probe",
      "breakdown": "multilevel_projected_fgmres_residual_gate_not_met",
      "claim_boundary": "Recursive projected V-cycle FGMRES uses distributed structural-node DOF modes as the first-level orthogonal projection basis when authored free_global_dof metadata is available, then algebraic RCM aggregation on coarser levels. Sparse matvecs, restrictions, prolongations, Jacobi smoothing, Arnoldi updates, least-squares solves, and coarse dense solves run on the ROCm torch device; CPU work is hierarchy setup only and cannot promote closure without full assembled CSR residual replay."
    },
    {
      "backend": "rocm_torch_sparse_multilevel_projected_fgmres",
      "device": "cuda:0",
      "converged": false,
      "aggregate_count": 256,
      "projector_kind": "distributed_structural_node_dof_orthogonal_projection",
      "level_count": 4,
      "levels": [
        {
          "level": 0,
          "size": 33932,
          "nnz": 823815,
          "projector_columns": 1225,
          "projector_nnz": 369392,
          "projector_smoothing_steps_applied": 1
        },
        {
          "level": 1,
          "size": 1225,
          "nnz": 212837,
          "projector_columns": 307,
          "projector_nnz": 74548,
          "projector_smoothing_steps_applied": 1
        },
        {
          "level": 2,
          "size": 307,
          "nnz": 77853,
          "projector_columns": 77,
          "projector_nnz": 19555,
          "projector_smoothing_steps_applied": 1
        },
        {
          "level": 3,
          "size": 77,
          "nnz": 4907,
          "projector_columns": null,
          "projector_nnz": null,
          "projector_smoothing_steps_applied": null
        }
      ],
      "pre_smooth_steps": 1,
      "post_smooth_steps": 1,
      "smoother_weight": 0.05,
      "coarse_regularization_factor": 1e-08,
      "prolongation_smoothing_steps": 1,
      "prolongation_smoothing_weight": 0.05,
      "projector_smoothing_steps_applied": [
        1,
        1,
        1
      ],
      "krylov_method": "fgmres",
      "restart_dimension": 24,
      "restart_cycles": 2,
      "iteration_count": 48,
      "max_iterations": 48,
      "initial_residual_inf_n": 32.47377433333335,
      "residual_inf_n": 25.298022542458124,
      "best_residual_inf_n": 25.298022542458124,
      "relative_residual_inf": 0.7790293263352042,
      "rhs_inf_n": 32.47377433333335,
      "threshold_n": 0.001,
      "residual_history_head": [
        32.47377433333335,
        32.43652638276985,
        32.09681481847513,
        30.257609366096574,
        29.039560891968016,
        28.26015331013241,
        28.750243500208484,
        27.918330073520014
      ],
      "residual_history_tail": [
        27.829774651852997,
        27.174724861853655,
        26.48378229886159,
        26.55690406722456,
        26.845006854490748,
        26.092787263070736,
        25.628019785145582,
        25.298022542458124
      ],
      "solve_seconds": 0.8763569239999924,
      "device_residency_ratio": 1.0,
      "vcycle_count": 48,
      "host_dense_solve_fallback_count": 0,
      "host_copy_bytes": 355329132,
      "hip_kernel_invocation_count": 1344,
      "solver_path_kind": "rocm_sparse_multilevel_projected_fgmres_probe",
      "breakdown": "multilevel_projected_fgmres_residual_gate_not_met",
      "claim_boundary": "Recursive projected V-cycle FGMRES uses distributed structural-node DOF modes as the first-level orthogonal projection basis when authored free_global_dof metadata is available, then algebraic RCM aggregation on coarser levels. Sparse matvecs, restrictions, prolongations, Jacobi smoothing, Arnoldi updates, least-squares solves, and coarse dense solves run on the ROCm torch device; CPU work is hierarchy setup only and cannot promote closure without full assembled CSR residual replay."
    },
    {
      "backend": "rocm_torch_sparse_multilevel_projected_fgmres",
      "device": "cuda:0",
      "converged": false,
      "aggregate_count": 512,
      "projector_kind": "distributed_structural_node_dof_orthogonal_projection",
      "level_count": 4,
      "levels": [
        {
          "level": 0,
          "size": 33932,
          "nnz": 823815,
          "projector_columns": 2407,
          "projector_nnz": 416272,
          "projector_smoothing_steps_applied": 1
        },
        {
          "level": 1,
          "size": 2407,
          "nnz": 423333,
          "projector_columns": 602,
          "projector_nnz": 157792,
          "projector_smoothing_steps_applied": 1
        },
        {
          "level": 2,
          "size": 602,
          "nnz": 295290,
          "projector_columns": 151,
          "projector_nnz": 73977,
          "projector_smoothing_steps_applied": 1
        },
        {
          "level": 3,
          "size": 151,
          "nnz": 18511,
          "projector_columns": null,
          "projector_nnz": null,
          "projector_smoothing_steps_applied": null
        }
      ],
      "pre_smooth_steps": 1,
      "post_smooth_steps": 1,
      "smoother_weight": 0.05,
      "coarse_regularization_factor": 1e-08,
      "prolongation_smoothing_steps": 1,
      "prolongation_smoothing_weight": 0.02,
      "projector_smoothing_steps_applied": [
        1,
        1,
        1
      ],
      "krylov_method": "fgmres",
      "restart_dimension": 24,
      "restart_cycles": 2,
      "iteration_count": 48,
      "max_iterations": 48,
      "initial_residual_inf_n": 32.47377433333335,
      "residual_inf_n": 24.324310976328043,
      "best_residual_inf_n": 24.324310976328043,
      "relative_residual_inf": 0.7490447746124745,
      "rhs_inf_n": 32.47377433333335,
      "threshold_n": 0.001,
      "residual_history_head": [
        32.47377433333335,
        33.0640402480153,
        30.93406193292241,
        28.72821318090427,
        27.525118805012205,
        27.00336748333812,
        27.711861395037918,
        28.189713423318814
      ],
      "residual_history_tail": [
        26.91338765036194,
        26.871747669562318,
        26.65146492619111,
        26.002504006355714,
        25.330219347378467,
        24.896663688035677,
        24.324310976328043,
        24.33429509720904
      ],
      "solve_seconds": 1.2943172350005625,
      "device_residency_ratio": 1.0,
      "vcycle_count": 48,
      "host_dense_solve_fallback_count": 0,
      "host_copy_bytes": 692971824,
      "hip_kernel_invocation_count": 1344,
      "solver_path_kind": "rocm_sparse_multilevel_projected_fgmres_probe",
      "breakdown": "multilevel_projected_fgmres_residual_gate_not_met",
      "claim_boundary": "Recursive projected V-cycle FGMRES uses distributed structural-node DOF modes as the first-level orthogonal projection basis when authored free_global_dof metadata is available, then algebraic RCM aggregation on coarser levels. Sparse matvecs, restrictions, prolongations, Jacobi smoothing, Arnoldi updates, least-squares solves, and coarse dense solves run on the ROCm torch device; CPU work is hierarchy setup only and cannot promote closure without full assembled CSR residual replay."
    },
    {
      "backend": "rocm_torch_sparse_multilevel_projected_fgmres",
      "device": "cuda:0",
      "converged": false,
      "aggregate_count": 512,
      "projector_kind": "distributed_structural_node_dof_orthogonal_projection",
      "level_count": 4,
      "levels": [
        {
          "level": 0,
          "size": 33932,
          "nnz": 823815,
          "projector_columns": 2407,
          "projector_nnz": 416272,
          "projector_smoothing_steps_applied": 1
        },
        {
          "level": 1,
          "size": 2407,
          "nnz": 423333,
          "projector_columns": 602,
          "projector_nnz": 157792,
          "projector_smoothing_steps_applied": 1
        },
        {
          "level": 2,
          "size": 602,
          "nnz": 295290,
          "projector_columns": 151,
          "projector_nnz": 73977,
          "projector_smoothing_steps_applied": 1
        },
        {
          "level": 3,
          "size": 151,
          "nnz": 18511,
          "projector_columns": null,
          "projector_nnz": null,
          "projector_smoothing_steps_applied": null
        }
      ],
      "pre_smooth_steps": 1,
      "post_smooth_steps": 1,
      "smoother_weight": 0.05,
      "coarse_regularization_factor": 1e-08,
      "prolongation_smoothing_steps": 1,
      "prolongation_smoothing_weight": 0.05,
      "projector_smoothing_steps_applied": [
        1,
        1,
        1
      ],
      "krylov_method": "fgmres",
      "restart_dimension": 24,
      "restart_cycles": 2,
      "iteration_count": 48,
      "max_iterations": 48,
      "initial_residual_inf_n": 32.47377433333335,
      "residual_inf_n": 24.70482112844354,
      "best_residual_inf_n": 24.70482112844354,
      "relative_residual_inf": 0.7607622346221944,
      "rhs_inf_n": 32.47377433333335,
      "threshold_n": 0.001,
      "residual_history_head": [
        32.47377433333335,
        32.965892865327746,
        31.198609905692905,
        29.28020862242518,
        28.07348894724179,
        27.22355308606919,
        27.419784452280382,
        27.989862957115133
      ],
      "residual_history_tail": [
        27.05702646958438,
        27.029920675757733,
        26.836589580038936,
        26.22144307972663,
        25.64804658316227,
        25.347998443492873,
        24.953329235497936,
        24.70482112844354
      ],
      "solve_seconds": 1.2516738140002417,
      "device_residency_ratio": 1.0,
      "vcycle_count": 48,
      "host_dense_solve_fallback_count": 0,
      "host_copy_bytes": 692971824,
      "hip_kernel_invocation_count": 1344,
      "solver_path_kind": "rocm_sparse_multilevel_projected_fgmres_probe",
      "breakdown": "multilevel_projected_fgmres_residual_gate_not_met",
      "claim_boundary": "Recursive projected V-cycle FGMRES uses distributed structural-node DOF modes as the first-level orthogonal projection basis when authored free_global_dof metadata is available, then algebraic RCM aggregation on coarser levels. Sparse matvecs, restrictions, prolongations, Jacobi smoothing, Arnoldi updates, least-squares solves, and coarse dense solves run on the ROCm torch device; CPU work is hierarchy setup only and cannot promote closure without full assembled CSR residual replay."
    },
    {
      "backend": "rocm_torch_sparse_multilevel_projected_fgmres",
      "device": "cuda:0",
      "converged": false,
      "aggregate_count": 512,
      "projector_kind": "distributed_structural_node_dof_orthogonal_projection",
      "level_count": 5,
      "levels": [
        {
          "level": 0,
          "size": 33932,
          "nnz": 823815,
          "projector_columns": 2407,
          "projector_nnz": 416272,
          "projector_smoothing_steps_applied": 1
        },
        {
          "level": 1,
          "size": 2407,
          "nnz": 423333,
          "projector_columns": 602,
          "projector_nnz": 157792,
          "projector_smoothing_steps_applied": 1
        },
        {
          "level": 2,
          "size": 602,
          "nnz": 295290,
          "projector_columns": 151,
          "projector_nnz": 73977,
          "projector_smoothing_steps_applied": 1
        },
        {
          "level": 3,
          "size": 151,
          "nnz": 18511,
          "projector_columns": 38,
          "projector_nnz": 4639,
          "projector_smoothing_steps_applied": 1
        },
        {
          "level": 4,
          "size": 38,
          "nnz": 1160,
          "projector_columns": null,
          "projector_nnz": null,
          "projector_smoothing_steps_applied": null
        }
      ],
      "pre_smooth_steps": 1,
      "post_smooth_steps": 1,
      "smoother_weight": 0.02,
      "coarse_regularization_factor": 1e-08,
      "prolongation_smoothing_steps": 1,
      "prolongation_smoothing_weight": 0.02,
      "projector_smoothing_steps_applied": [
        1,
        1,
        1,
        1
      ],
      "krylov_method": "fgmres",
      "restart_dimension": 24,
      "restart_cycles": 2,
      "iteration_count": 48,
      "max_iterations": 48,
      "initial_residual_inf_n": 32.47377433333335,
      "residual_inf_n": 25.203343712207634,
      "best_residual_inf_n": 25.203343712207634,
      "relative_residual_inf": 0.7761137788759331,
      "rhs_inf_n": 32.47377433333335,
      "threshold_n": 0.001,
      "residual_history_head": [
        32.47377433333335,
        32.5550682311589,
        33.391634650292175,
        29.750898725510808,
        28.303487388786323,
        27.358642049727067,
        27.15788966653924,
        27.800575876064148
      ],
      "residual_history_tail": [
        27.196864959205094,
        27.515866645135972,
        27.922732982585934,
        27.617132631399674,
        27.019363556817947,
        26.733724808205025,
        26.574161761105884,
        26.170103469662763
      ],
      "solve_seconds": 1.2606841679989884,
      "device_residency_ratio": 1.0,
      "vcycle_count": 48,
      "host_dense_solve_fallback_count": 0,
      "host_copy_bytes": 692917224,
      "hip_kernel_invocation_count": 1680,
      "solver_path_kind": "rocm_sparse_multilevel_projected_fgmres_probe",
      "breakdown": "multilevel_projected_fgmres_residual_gate_not_met",
      "claim_boundary": "Recursive projected V-cycle FGMRES uses distributed structural-node DOF modes as the first-level orthogonal projection basis when authored free_global_dof metadata is available, then algebraic RCM aggregation on coarser levels. Sparse matvecs, restrictions, prolongations, Jacobi smoothing, Arnoldi updates, least-squares solves, and coarse dense solves run on the ROCm torch device; CPU work is hierarchy setup only and cannot promote closure without full assembled CSR residual replay."
    }
  ],
  "claim_boundary": "Focused no-new-dependency ROCm torch recursive V-cycle FGMRES with energy-smoothed distributed structural-node DOF prolongation. This is not closure unless full assembled CSR residual replay meets the G9 gate."
}
